openmusickit/__init__.py
openmusickit/_nbdev.py
openmusickit/tonal_algebra.py
openmusickit-0.0.1.dist-info/LICENSE
openmusickit-0.0.1.dist-info/METADATA
openmusickit-0.0.1.dist-info/WHEEL
openmusickit-0.0.1.dist-info/entry_points.txt
openmusickit-0.0.1.dist-info/top_level.txt
openmusickit-0.0.1.dist-info/RECORD
