Metadata-Version: 2.1
Name: openmusickit
Version: 0.0.1
Summary: Tools for computational music analysis
Home-page: https://github.com/openmusickit/openmusickit/tree/master/
Author: Adam Michael Wood
Author-email: adamwood@google.com
License: Apache Software License 2.0
Keywords: music
Platform: UNKNOWN
Classifier: Development Status :: 3 - Alpha
Classifier: Intended Audience :: Developers
Classifier: Natural Language :: English
Classifier: Programming Language :: Python :: 3.6
Classifier: Programming Language :: Python :: 3.7
Classifier: Programming Language :: Python :: 3.8
Classifier: License :: OSI Approved :: Apache Software License
Requires-Python: >=3.6
License-File: LICENSE
Requires-Dist: pip
Requires-Dist: packaging
Requires-Dist: music21
Requires-Dist: networkx
Provides-Extra: dev
